OpenSeries/__init__.py
OpenSeries/bilangan_istimewa.py
OpenSeries/fisika.py
OpenSeries/matematika.py
OpenSeries/statistika.py
OpenSeries/util/__init__.py
OpenSeries/util/constant.py
OpenSeries/util/error.py
OpenSeriesBellshade-1.7.0.dist-info/LICENSE
OpenSeriesBellshade-1.7.0.dist-info/METADATA
OpenSeriesBellshade-1.7.0.dist-info/WHEEL
OpenSeriesBellshade-1.7.0.dist-info/top_level.txt
OpenSeriesBellshade-1.7.0.dist-info/RECORD
