Metadata-Version: 2.1
Name: OpenSeriesBellshade
Version: 1.7.0
Summary: library untuk membantu temen-temen dalam perhitungan matematika
Home-page: https://github.com/bellshade/OpenSeries
Author: bellshade wpu kelas terbuka
License: MIT
Project-URL: Homepage, https://github.com/bellshade/OpenSeries
Keywords: OpenSeriesBellshade,openseries,bellshade
Classifier: Intended Audience :: Developers
Classifier: License :: OSI Approved :: MIT License
Classifier: Natural Language :: English
Classifier: Natural Language :: Indonesian
Classifier: Programming Language :: Python :: 3.10
Classifier: Programming Language :: Python :: 3.11
Classifier: Programming Language :: Python :: 3.12
Requires-Python: >=3.10
License-File: LICENSE
Requires-Dist: colorama
Requires-Dist: numpy
